{
  "objectInfo" : {
    "id" : "cDoFRzAQQsuiC3qY1LGC03",
    "name" : "Statistics",
    "type" : "DTEMPLATE",
    "metadata" : {
      "modelVersion" : {
        "major" : 0,
        "minor" : 0
      },
      "repoInfo" : {
        "repoHandle" : "011H9J170000000000UD"
      },
      "contextAttributes" : [ {
        "name" : "id",
        "value" : "@1"
      } ],
      "additionalInfo" : {
        "description" : "",
        "contentType" : "JSON",
        "documentState" : "VALID"
      }
    }
  },
  "dataFileExtension" : "zip",
  "objectRefs" : [ {
    "id" : "8DOnVp3lYsohGgXgQwIbgB",
    "name" : "Activity_Log",
    "type" : "BSERVICE",
    "metadata" : {
      "modelVersion" : {
        "major" : 0,
        "minor" : 0
      },
      "repoInfo" : {
        "repoHandle" : "011H9J27000000000005"
      },
      "contextAttributes" : [ {
        "name" : "id",
        "value" : "@1"
      }, {
        "name" : "011H9J28000000000005",
        "value" : "8DOnVp3lYsohGgXgQwIbgB@Activity_Log"
      } ],
      "additionalInfo" : {
        "description" : "",
        "contentType" : "JSON",
        "documentState" : "VALID"
      }
    },
    "path" : "/Explore/Nandan"
  }, {
    "id" : "5sGgk2ZBbz1cxr5V2M41gD",
    "name" : "RV2_Login",
    "type" : "Connection",
    "metadata" : {
      "modelVersion" : {
        "major" : 0,
        "minor" : 0
      },
      "repoInfo" : {
        "repoHandle" : "011H9J0B000000000029"
      },
      "contextAttributes" : null,
      "additionalInfo" : {
        "description" : null,
        "contentType" : "JSON",
        "documentState" : "COMPLETE"
      }
    },
    "path" : "/SYS"
  }, {
    "id" : "6ZHqvbPwYVNcYsiO6JV5OP",
    "name" : "NHM_ORCL",
    "type" : "Connection",
    "metadata" : {
      "modelVersion" : {
        "major" : 0,
        "minor" : 0
      },
      "repoInfo" : {
        "repoHandle" : "011H9J0B00000000002F"
      },
      "contextAttributes" : null,
      "additionalInfo" : {
        "description" : null,
        "contentType" : "JSON",
        "documentState" : "COMPLETE"
      }
    },
    "path" : "/SYS"
  } ]
}